.foundryrc
.gitignore
.travis.yml
CHANGELOG.rst
MANIFEST.in
README.rst
UNLICENSE
Vagrantfile
release.sh
requirements.txt
setup.py
test.sh
docs/getting_started.py
docs/tests.png
sublime_plugin_tests/__init__.py
sublime_plugin_tests/framework.py
sublime_plugin_tests.egg-info/PKG-INFO
sublime_plugin_tests.egg-info/SOURCES.txt
sublime_plugin_tests.egg-info/dependency_links.txt
sublime_plugin_tests.egg-info/pbr.json
sublime_plugin_tests.egg-info/requires.txt
sublime_plugin_tests.egg-info/top_level.txt
sublime_plugin_tests/utils/__init__.py
sublime_plugin_tests/utils/selection.py