Metadata-Version: 1.1
Name: sublime-plugin-tests
Version: 2.0.0
Summary: Testing framework for Sublime Text plugins
Home-page: https://github.com/twolfson/sublime-plugin-tests
Author: Todd Wolfson
Author-email: todd@twolfson.com
License: UNLICENSE
Download-URL: https://github.com/twolfson/sublime-plugin-tests/archive/master.zip
Keywords: sublime text,plugin,test,framework,tdd
Platform: UNKNOWN
Classifier: Development Status :: 3 - Alpha
Classifier: Intended Audience :: Developers
Classifier: License :: Public Domain
Classifier: Operating System :: OS Independent
Classifier: Programming Language :: Python
Classifier: Topic :: Software Development :: Testing
Classifier: Topic :: Text Editors
